README.md
setup.py
cilantro/__init__.py
cilantro/motors.py
cilantro/robot.py
cilantro/sensors.py
rr_cilantro.egg-info/PKG-INFO
rr_cilantro.egg-info/SOURCES.txt
rr_cilantro.egg-info/dependency_links.txt
rr_cilantro.egg-info/not-zip-safe
rr_cilantro.egg-info/requires.txt
rr_cilantro.egg-info/top_level.txt