Metadata-Version: 1.2
Name: rr-cilantro
Version: 0.1.0
Summary: A CamJam Edukit 3 Wrapper
Home-page: https://github.com/RedRiverSoftware/cilantro/
Author: Red River Software
Author-email: os@river.red
License: UNKNOWN
Keywords: cilantro,robot,camjam
Platform: any
Classifier: Development Status :: 3 - Alpha
Classifier: Intended Audience :: Developers
Classifier: Operating System :: OS Independent
Classifier: Programming Language :: Python
Classifier: Programming Language :: Python :: 3 :: Only
Classifier: Programming Language :: Python :: 3.4
Classifier: Programming Language :: Python :: 3.5
Classifier: Programming Language :: Python :: 3.6
Classifier: Topic :: Software Development :: Libraries :: Python Modules
Requires-Python: >=3.4
